<?xml version = "1.0" encoding = "UTF-8"?>
<Stage>
<Zone>
<ZoneInfo Name = "0" Left = "39" Top = "44" Right = "42" Bottom = "49" AIStep = "0" CanPK = "false" CanPrivateShop = "false" EnterScript = "NULL" LeaveScript = "NULL">
</ZoneInfo>
<ZoneInfo Name = "1" Left = "39" Top = "51" Right = "44" Bottom = "57" AIStep = "0" CanPK = "false" CanPrivateShop = "false" EnterScript = "NULL" LeaveScript = "NULL">
</ZoneInfo>
<ZoneInfo Name = "2" Left = "39" Top = "49" Right = "44" Bottom = "55" AIStep = "0" CanPK = "false" CanPrivateShop = "false" EnterScript = "NULL" LeaveScript = "NULL">
</ZoneInfo>
<ZoneInfo Name = "3" Left = "57" Top = "50" Right = "63" Bottom = "58" AIStep = "0" CanPK = "false" CanPrivateShop = "false" EnterScript = "NULL" LeaveScript = "NULL">
</ZoneInfo>
<ZoneInfo Name = "4" Left = "43" Top = "72" Right = "50" Bottom = "78" AIStep = "0" CanPK = "false" CanPrivateShop = "false" EnterScript = "NULL" LeaveScript = "NULL">
</ZoneInfo>
<ZoneInfo Name = "5" Left = "41" Top = "74" Right = "47" Bottom = "79" AIStep = "0" CanPK = "false" CanPrivateShop = "false" EnterScript = "NULL" LeaveScript = "NULL">
</ZoneInfo>
<ZoneInfo Name = "7" Left = "47" Top = "70" Right = "51" Bottom = "75" AIStep = "0" CanPK = "false" CanPrivateShop = "false" EnterScript = "NULL" LeaveScript = "NULL">
</ZoneInfo>
<ZoneInfo Name = "8" Left = "44" Top = "77" Right = "50" Bottom = "82" AIStep = "0" CanPK = "false" CanPrivateShop = "false" EnterScript = "NULL" LeaveScript = "NULL">
</ZoneInfo>
<ZoneInfo Name = "9" Left = "49" Top = "74" Right = "54" Bottom = "78" AIStep = "0" CanPK = "false" CanPrivateShop = "false" EnterScript = "NULL" LeaveScript = "NULL">
</ZoneInfo>
<ZoneInfo Name = "11" Left = "82" Top = "47" Right = "87" Bottom = "51" AIStep = "0" CanPK = "false" CanPrivateShop = "false" EnterScript = "NULL" LeaveScript = "NULL">
</ZoneInfo>
<ZoneInfo Name = "12" Left = "80" Top = "51" Right = "87" Bottom = "54" AIStep = "0" CanPK = "false" CanPrivateShop = "false" EnterScript = "NULL" LeaveScript = "NULL">
</ZoneInfo>
<ZoneInfo Name = "13" Left = "81" Top = "37" Right = "87" Bottom = "42" AIStep = "0" CanPK = "false" CanPrivateShop = "false" EnterScript = "NULL" LeaveScript = "NULL">
</ZoneInfo>
<ZoneInfo Name = "14" Left = "81" Top = "41" Right = "87" Bottom = "48" AIStep = "0" CanPK = "false" CanPrivateShop = "false" EnterScript = "NULL" LeaveScript = "NULL">
</ZoneInfo>
<ZoneInfo Name = "15" Left = "78" Top = "49" Right = "85" Bottom = "54" AIStep = "0" CanPK = "false" CanPrivateShop = "false" EnterScript = "NULL" LeaveScript = "NULL">
</ZoneInfo>
<ZoneInfo Name = "17" Left = "73" Top = "61" Right = "79" Bottom = "65" AIStep = "0" CanPK = "false" CanPrivateShop = "false" EnterScript = "NULL" LeaveScript = "NULL">
</ZoneInfo>
<ZoneInfo Name = "20" Left = "83" Top = "68" Right = "87" Bottom = "75" AIStep = "0" CanPK = "false" CanPrivateShop = "false" EnterScript = "NULL" LeaveScript = "NULL">
</ZoneInfo>
<ZoneInfo Name = "23" Left = "59" Top = "85" Right = "66" Bottom = "88" AIStep = "0" CanPK = "false" CanPrivateShop = "false" EnterScript = "NULL" LeaveScript = "NULL">
</ZoneInfo>
<ZoneInfo Name = "25" Left = "81" Top = "67" Right = "86" Bottom = "72" AIStep = "0" CanPK = "false" CanPrivateShop = "false" EnterScript = "NULL" LeaveScript = "NULL">
</ZoneInfo>
<ZoneInfo Name = "26" Left = "78" Top = "82" Right = "85" Bottom = "86" AIStep = "0" CanPK = "false" CanPrivateShop = "false" EnterScript = "NULL" LeaveScript = "NULL">
</ZoneInfo>
<ZoneInfo Name = "27" Left = "75" Top = "83" Right = "81" Bottom = "86" AIStep = "0" CanPK = "false" CanPrivateShop = "false" EnterScript = "NULL" LeaveScript = "NULL">
</ZoneInfo>
</Zone>
<Monster>
<MonsterGroup>
<MonsterGroupInfo ZoneId = "0" X = "39.8504" Y = "45.1912" RandRange = "true" Dir = "0" Index = "21197" Number = "1" Relife = "150000" County = "0" Enable = "true" Hide = "false" DeadScript = "NULL" LuaScript = "NULL" AIValue = "1000">
</MonsterGroupInfo>
</MonsterGroup>
<MonsterGroup>
<MonsterGroupInfo ZoneId = "0" X = "42" Y = "45.601" RandRange = "true" Dir = "0" Index = "21197" Number = "1" Relife = "150000" County = "0" Enable = "true" Hide = "false" DeadScript = "NULL" LuaScript = "NULL" AIValue = "1000">
</MonsterGroupInfo>
</MonsterGroup>
<MonsterGroup>
<MonsterGroupInfo ZoneId = "0" X = "42" Y = "47.8637" RandRange = "true" Dir = "0" Index = "21197" Number = "1" Relife = "150000" County = "0" Enable = "true" Hide = "false" DeadScript = "NULL" LuaScript = "NULL" AIValue = "1000">
</MonsterGroupInfo>
</MonsterGroup>
<MonsterGroup>
<MonsterGroupInfo ZoneId = "0" X = "40.7219" Y = "49" RandRange = "true" Dir = "0" Index = "21197" Number = "1" Relife = "150000" County = "0" Enable = "true" Hide = "false" DeadScript = "NULL" LuaScript = "NULL" AIValue = "1000">
</MonsterGroupInfo>
</MonsterGroup>
<MonsterGroup>
<MonsterGroupInfo ZoneId = "0" X = "42" Y = "49" RandRange = "true" Dir = "0" Index = "21197" Number = "1" Relife = "150000" County = "0" Enable = "true" Hide = "false" DeadScript = "NULL" LuaScript = "NULL" AIValue = "1000">
</MonsterGroupInfo>
</MonsterGroup>
<MonsterGroup>
<MonsterGroupInfo ZoneId = "1" X = "40.0431" Y = "51.1752" RandRange = "true" Dir = "0" Index = "21197" Number = "1" Relife = "150000" County = "0" Enable = "true" Hide = "false" DeadScript = "NULL" LuaScript = "NULL" AIValue = "1000">
</MonsterGroupInfo>
</MonsterGroup>
<MonsterGroup>
<MonsterGroupInfo ZoneId = "1" X = "40.3613" Y = "54.7681" RandRange = "true" Dir = "0" Index = "21197" Number = "1" Relife = "150000" County = "0" Enable = "true" Hide = "false" DeadScript = "NULL" LuaScript = "NULL" AIValue = "1000">
</MonsterGroupInfo>
</MonsterGroup>
<MonsterGroup>
<MonsterGroupInfo ZoneId = "1" X = "41.233" Y = "56.3208" RandRange = "true" Dir = "0" Index = "21197" Number = "1" Relife = "150000" County = "0" Enable = "true" Hide = "false" DeadScript = "NULL" LuaScript = "NULL" AIValue = "1000">
</MonsterGroupInfo>
</MonsterGroup>
<MonsterGroup>
<MonsterGroupInfo ZoneId = "1" X = "44" Y = "56.2976" RandRange = "true" Dir = "0" Index = "21197" Number = "1" Relife = "150000" County = "0" Enable = "true" Hide = "false" DeadScript = "NULL" LuaScript = "NULL" AIValue = "1000">
</MonsterGroupInfo>
</MonsterGroup>
<MonsterGroup>
<MonsterGroupInfo ZoneId = "1" X = "43.8745" Y = "53.2307" RandRange = "true" Dir = "0" Index = "21197" Number = "1" Relife = "150000" County = "0" Enable = "true" Hide = "false" DeadScript = "NULL" LuaScript = "NULL" AIValue = "1000">
</MonsterGroupInfo>
</MonsterGroup>
<MonsterGroup>
<MonsterGroupInfo ZoneId = "1" X = "43.8548" Y = "52.4697" RandRange = "true" Dir = "0" Index = "21197" Number = "1" Relife = "150000" County = "0" Enable = "true" Hide = "false" DeadScript = "NULL" LuaScript = "NULL" AIValue = "1000">
</MonsterGroupInfo>
</MonsterGroup>
<MonsterGroup>
<MonsterGroupInfo ZoneId = "2" X = "40.4374" Y = "50.2511" RandRange = "true" Dir = "0" Index = "21197" Number = "1" Relife = "150000" County = "0" Enable = "true" Hide = "false" DeadScript = "NULL" LuaScript = "NULL" AIValue = "1000">
</MonsterGroupInfo>
</MonsterGroup>
<MonsterGroup>
<MonsterGroupInfo ZoneId = "2" X = "40.0121" Y = "53.5101" RandRange = "true" Dir = "0" Index = "21197" Number = "1" Relife = "150000" County = "0" Enable = "true" Hide = "false" DeadScript = "NULL" LuaScript = "NULL" AIValue = "1000">
</MonsterGroupInfo>
</MonsterGroup>
<MonsterGroup>
<MonsterGroupInfo ZoneId = "2" X = "40.3806" Y = "55" RandRange = "true" Dir = "0" Index = "21197" Number = "1" Relife = "150000" County = "0" Enable = "true" Hide = "false" DeadScript = "NULL" LuaScript = "NULL" AIValue = "1000">
</MonsterGroupInfo>
</MonsterGroup>
<MonsterGroup>
<MonsterGroupInfo ZoneId = "2" X = "43.6579" Y = "54.7212" RandRange = "true" Dir = "0" Index = "21197" Number = "1" Relife = "150000" County = "0" Enable = "true" Hide = "false" DeadScript = "NULL" LuaScript = "NULL" AIValue = "1000">
</MonsterGroupInfo>
</MonsterGroup>
<MonsterGroup>
<MonsterGroupInfo ZoneId = "2" X = "43.8875" Y = "51.6074" RandRange = "true" Dir = "0" Index = "21197" Number = "1" Relife = "150000" County = "0" Enable = "true" Hide = "false" DeadScript = "NULL" LuaScript = "NULL" AIValue = "1000">
</MonsterGroupInfo>
</MonsterGroup>
<MonsterGroup>
<MonsterGroupInfo ZoneId = "2" X = "43.7714" Y = "51.1956" RandRange = "true" Dir = "0" Index = "21197" Number = "1" Relife = "150000" County = "0" Enable = "true" Hide = "false" DeadScript = "NULL" LuaScript = "NULL" AIValue = "1000">
</MonsterGroupInfo>
</MonsterGroup>
<MonsterGroup>
<MonsterGroupInfo ZoneId = "2" X = "42.3731" Y = "50.7011" RandRange = "true" Dir = "0" Index = "21197" Number = "1" Relife = "150000" County = "0" Enable = "true" Hide = "false" DeadScript = "NULL" LuaScript = "NULL" AIValue = "1000">
</MonsterGroupInfo>
</MonsterGroup>
<MonsterGroup>
<MonsterGroupInfo ZoneId = "2" X = "41.801" Y = "52.2524" RandRange = "true" Dir = "0" Index = "21197" Number = "1" Relife = "150000" County = "0" Enable = "true" Hide = "false" DeadScript = "NULL" LuaScript = "NULL" AIValue = "1000">
</MonsterGroupInfo>
</MonsterGroup>
<MonsterGroup>
<MonsterGroupInfo ZoneId = "4" X = "44.2828" Y = "73.2682" RandRange = "true" Dir = "0" Index = "21197" Number = "1" Relife = "150000" County = "0" Enable = "true" Hide = "false" DeadScript = "NULL" LuaScript = "NULL" AIValue = "1000">
</MonsterGroupInfo>
</MonsterGroup>
<MonsterGroup>
<MonsterGroupInfo ZoneId = "4" X = "44.6634" Y = "75.9553" RandRange = "true" Dir = "0" Index = "21197" Number = "1" Relife = "150000" County = "0" Enable = "true" Hide = "false" DeadScript = "NULL" LuaScript = "NULL" AIValue = "1000">
</MonsterGroupInfo>
</MonsterGroup>
<MonsterGroup>
<MonsterGroupInfo ZoneId = "4" X = "44.9235" Y = "77.0011" RandRange = "true" Dir = "0" Index = "21197" Number = "1" Relife = "150000" County = "0" Enable = "true" Hide = "false" DeadScript = "NULL" LuaScript = "NULL" AIValue = "1000">
</MonsterGroupInfo>
</MonsterGroup>
<MonsterGroup>
<MonsterGroupInfo ZoneId = "4" X = "49.7396" Y = "77.5256" RandRange = "true" Dir = "0" Index = "21197" Number = "1" Relife = "150000" County = "0" Enable = "true" Hide = "false" DeadScript = "NULL" LuaScript = "NULL" AIValue = "1000">
</MonsterGroupInfo>
</MonsterGroup>
<MonsterGroup>
<MonsterGroupInfo ZoneId = "4" X = "49.499" Y = "73.3529" RandRange = "true" Dir = "0" Index = "21197" Number = "1" Relife = "150000" County = "0" Enable = "true" Hide = "false" DeadScript = "NULL" LuaScript = "NULL" AIValue = "1000">
</MonsterGroupInfo>
</MonsterGroup>
<MonsterGroup>
<MonsterGroupInfo ZoneId = "4" X = "48.9285" Y = "72.8511" RandRange = "true" Dir = "0" Index = "21197" Number = "1" Relife = "150000" County = "0" Enable = "true" Hide = "false" DeadScript = "NULL" LuaScript = "NULL" AIValue = "1000">
</MonsterGroupInfo>
</MonsterGroup>
<MonsterGroup>
<MonsterGroupInfo ZoneId = "3" X = "58.9361" Y = "51.2359" RandRange = "true" Dir = "0" Index = "21197" Number = "1" Relife = "150000" County = "0" Enable = "true" Hide = "false" DeadScript = "NULL" LuaScript = "NULL" AIValue = "1000">
</MonsterGroupInfo>
</MonsterGroup>
<MonsterGroup>
<MonsterGroupInfo ZoneId = "3" X = "58.079" Y = "54.3249" RandRange = "true" Dir = "0" Index = "21197" Number = "1" Relife = "150000" County = "0" Enable = "true" Hide = "false" DeadScript = "NULL" LuaScript = "NULL" AIValue = "1000">
</MonsterGroupInfo>
</MonsterGroup>
<MonsterGroup>
<MonsterGroupInfo ZoneId = "3" X = "58.2442" Y = "56.9336" RandRange = "true" Dir = "0" Index = "21197" Number = "1" Relife = "150000" County = "0" Enable = "true" Hide = "false" DeadScript = "NULL" LuaScript = "NULL" AIValue = "1000">
</MonsterGroupInfo>
</MonsterGroup>
<MonsterGroup>
<MonsterGroupInfo ZoneId = "3" X = "60.8774" Y = "57.5073" RandRange = "true" Dir = "0" Index = "21197" Number = "1" Relife = "150000" County = "0" Enable = "true" Hide = "false" DeadScript = "NULL" LuaScript = "NULL" AIValue = "1000">
</MonsterGroupInfo>
</MonsterGroup>
<MonsterGroup>
<MonsterGroupInfo ZoneId = "3" X = "63" Y = "56.9057" RandRange = "true" Dir = "0" Index = "21197" Number = "1" Relife = "150000" County = "0" Enable = "true" Hide = "false" DeadScript = "NULL" LuaScript = "NULL" AIValue = "1000">
</MonsterGroupInfo>
</MonsterGroup>
<MonsterGroup>
<MonsterGroupInfo ZoneId = "3" X = "61.6389" Y = "52.3619" RandRange = "true" Dir = "0" Index = "21197" Number = "1" Relife = "150000" County = "0" Enable = "true" Hide = "false" DeadScript = "NULL" LuaScript = "NULL" AIValue = "1000">
</MonsterGroupInfo>
</MonsterGroup>
<MonsterGroup>
<MonsterGroupInfo ZoneId = "5" X = "43.2605" Y = "75.039" RandRange = "true" Dir = "0" Index = "21197" Number = "1" Relife = "150000" County = "0" Enable = "true" Hide = "false" DeadScript = "NULL" LuaScript = "NULL" AIValue = "1000">
</MonsterGroupInfo>
</MonsterGroup>
<MonsterGroup>
<MonsterGroupInfo ZoneId = "5" X = "41.67" Y = "76.5323" RandRange = "true" Dir = "0" Index = "21197" Number = "1" Relife = "150000" County = "0" Enable = "true" Hide = "false" DeadScript = "NULL" LuaScript = "NULL" AIValue = "1000">
</MonsterGroupInfo>
</MonsterGroup>
<MonsterGroup>
<MonsterGroupInfo ZoneId = "5" X = "43.0624" Y = "77.9851" RandRange = "true" Dir = "0" Index = "21197" Number = "1" Relife = "150000" County = "0" Enable = "true" Hide = "false" DeadScript = "NULL" LuaScript = "NULL" AIValue = "1000">
</MonsterGroupInfo>
</MonsterGroup>
<MonsterGroup>
<MonsterGroupInfo ZoneId = "5" X = "46.2072" Y = "78.4431" RandRange = "true" Dir = "0" Index = "21197" Number = "1" Relife = "150000" County = "0" Enable = "true" Hide = "false" DeadScript = "NULL" LuaScript = "NULL" AIValue = "1000">
</MonsterGroupInfo>
</MonsterGroup>
<MonsterGroup>
<MonsterGroupInfo ZoneId = "5" X = "47" Y = "76.608" RandRange = "true" Dir = "0" Index = "21197" Number = "1" Relife = "150000" County = "0" Enable = "true" Hide = "false" DeadScript = "NULL" LuaScript = "NULL" AIValue = "1000">
</MonsterGroupInfo>
</MonsterGroup>
<MonsterGroup>
<MonsterGroupInfo ZoneId = "5" X = "46.3983" Y = "74.1422" RandRange = "true" Dir = "0" Index = "21197" Number = "1" Relife = "150000" County = "0" Enable = "true" Hide = "false" DeadScript = "NULL" LuaScript = "NULL" AIValue = "1000">
</MonsterGroupInfo>
</MonsterGroup>
<MonsterGroup>
<MonsterGroupInfo ZoneId = "6" X = "47.8787" Y = "70.8732" RandRange = "true" Dir = "0" Index = "21197" Number = "1" Relife = "150000" County = "0" Enable = "true" Hide = "false" DeadScript = "NULL" LuaScript = "NULL" AIValue = "1000">
</MonsterGroupInfo>
</MonsterGroup>
<MonsterGroup>
<MonsterGroupInfo ZoneId = "6" X = "47.8791" Y = "73.1392" RandRange = "true" Dir = "0" Index = "21197" Number = "1" Relife = "150000" County = "0" Enable = "true" Hide = "false" DeadScript = "NULL" LuaScript = "NULL" AIValue = "1000">
</MonsterGroupInfo>
</MonsterGroup>
<MonsterGroup>
<MonsterGroupInfo ZoneId = "6" X = "48.5277" Y = "75" RandRange = "true" Dir = "0" Index = "21197" Number = "1" Relife = "150000" County = "0" Enable = "true" Hide = "false" DeadScript = "NULL" LuaScript = "NULL" AIValue = "1000">
</MonsterGroupInfo>
</MonsterGroup>
<MonsterGroup>
<MonsterGroupInfo ZoneId = "6" X = "51" Y = "72.1717" RandRange = "true" Dir = "0" Index = "21197" Number = "1" Relife = "150000" County = "0" Enable = "true" Hide = "false" DeadScript = "NULL" LuaScript = "NULL" AIValue = "1000">
</MonsterGroupInfo>
</MonsterGroup>
<MonsterGroup>
<MonsterGroupInfo ZoneId = "6" X = "50.6674" Y = "70.278" RandRange = "true" Dir = "0" Index = "21197" Number = "1" Relife = "150000" County = "0" Enable = "true" Hide = "false" DeadScript = "NULL" LuaScript = "NULL" AIValue = "1000">
</MonsterGroupInfo>
</MonsterGroup>
<MonsterGroup>
<MonsterGroupInfo ZoneId = "6" X = "47.5895" Y = "71.8246" RandRange = "true" Dir = "0" Index = "21197" Number = "1" Relife = "150000" County = "0" Enable = "true" Hide = "false" DeadScript = "NULL" LuaScript = "NULL" AIValue = "1000">
</MonsterGroupInfo>
</MonsterGroup>
<MonsterGroup>
<MonsterGroupInfo ZoneId = "7" X = "45.2026" Y = "78.2249" RandRange = "true" Dir = "0" Index = "21197" Number = "1" Relife = "150000" County = "0" Enable = "true" Hide = "false" DeadScript = "NULL" LuaScript = "NULL" AIValue = "1000">
</MonsterGroupInfo>
</MonsterGroup>
<MonsterGroup>
<MonsterGroupInfo ZoneId = "7" X = "45.3392" Y = "80.5268" RandRange = "true" Dir = "0" Index = "21197" Number = "1" Relife = "150000" County = "0" Enable = "true" Hide = "false" DeadScript = "NULL" LuaScript = "NULL" AIValue = "1000">
</MonsterGroupInfo>
</MonsterGroup>
<MonsterGroup>
<MonsterGroupInfo ZoneId = "7" X = "45.4646" Y = "81.721" RandRange = "true" Dir = "0" Index = "21197" Number = "1" Relife = "150000" County = "0" Enable = "true" Hide = "false" DeadScript = "NULL" LuaScript = "NULL" AIValue = "1000">
</MonsterGroupInfo>
</MonsterGroup>
<MonsterGroup>
<MonsterGroupInfo ZoneId = "7" X = "47.985" Y = "81.7869" RandRange = "true" Dir = "0" Index = "21197" Number = "1" Relife = "150000" County = "0" Enable = "true" Hide = "false" DeadScript = "NULL" LuaScript = "NULL" AIValue = "1000">
</MonsterGroupInfo>
</MonsterGroup>
<MonsterGroup>
<MonsterGroupInfo ZoneId = "7" X = "47.9344" Y = "80.8658" RandRange = "true" Dir = "0" Index = "21197" Number = "1" Relife = "150000" County = "0" Enable = "true" Hide = "false" DeadScript = "NULL" LuaScript = "NULL" AIValue = "1000">
</MonsterGroupInfo>
</MonsterGroup>
<MonsterGroup>
<MonsterGroupInfo ZoneId = "7" X = "47.337" Y = "78.818" RandRange = "true" Dir = "0" Index = "21197" Number = "1" Relife = "150000" County = "0" Enable = "true" Hide = "false" DeadScript = "NULL" LuaScript = "NULL" AIValue = "1000">
</MonsterGroupInfo>
</MonsterGroup>
<MonsterGroup>
<MonsterGroupInfo ZoneId = "7" X = "48.9084" Y = "78.1341" RandRange = "true" Dir = "0" Index = "21197" Number = "1" Relife = "150000" County = "0" Enable = "true" Hide = "false" DeadScript = "NULL" LuaScript = "NULL" AIValue = "1000">
</MonsterGroupInfo>
</MonsterGroup>
<MonsterGroup>
<MonsterGroupInfo ZoneId = "7" X = "49.8475" Y = "79.4095" RandRange = "true" Dir = "0" Index = "21197" Number = "1" Relife = "150000" County = "0" Enable = "true" Hide = "false" DeadScript = "NULL" LuaScript = "NULL" AIValue = "1000">
</MonsterGroupInfo>
</MonsterGroup>
<MonsterGroup>
<MonsterGroupInfo ZoneId = "7" X = "49.4058" Y = "82" RandRange = "true" Dir = "0" Index = "21197" Number = "1" Relife = "150000" County = "0" Enable = "true" Hide = "false" DeadScript = "NULL" LuaScript = "NULL" AIValue = "1000">
</MonsterGroupInfo>
</MonsterGroup>
<MonsterGroup>
<MonsterGroupInfo ZoneId = "8" X = "50.536" Y = "74.6248" RandRange = "true" Dir = "0" Index = "21197" Number = "1" Relife = "150000" County = "0" Enable = "true" Hide = "false" DeadScript = "NULL" LuaScript = "NULL" AIValue = "1000">
</MonsterGroupInfo>
</MonsterGroup>
<MonsterGroup>
<MonsterGroupInfo ZoneId = "8" X = "49.3643" Y = "77.0322" RandRange = "true" Dir = "0" Index = "21197" Number = "1" Relife = "150000" County = "0" Enable = "true" Hide = "false" DeadScript = "NULL" LuaScript = "NULL" AIValue = "1000">
</MonsterGroupInfo>
</MonsterGroup>
<MonsterGroup>
<MonsterGroupInfo ZoneId = "8" X = "51.3274" Y = "77.8057" RandRange = "true" Dir = "0" Index = "21197" Number = "1" Relife = "150000" County = "0" Enable = "true" Hide = "false" DeadScript = "NULL" LuaScript = "NULL" AIValue = "1000">
</MonsterGroupInfo>
</MonsterGroup>
<MonsterGroup>
<MonsterGroupInfo ZoneId = "8" X = "53.418" Y = "75.8986" RandRange = "true" Dir = "0" Index = "21197" Number = "1" Relife = "150000" County = "0" Enable = "true" Hide = "false" DeadScript = "NULL" LuaScript = "NULL" AIValue = "1000">
</MonsterGroupInfo>
</MonsterGroup>
<MonsterGroup>
<MonsterGroupInfo ZoneId = "8" X = "52.8258" Y = "74.7306" RandRange = "true" Dir = "0" Index = "21197" Number = "1" Relife = "150000" County = "0" Enable = "true" Hide = "false" DeadScript = "NULL" LuaScript = "NULL" AIValue = "1000">
</MonsterGroupInfo>
</MonsterGroup>
<MonsterGroup>
<MonsterGroupInfo ZoneId = "8" X = "53.981" Y = "78" RandRange = "true" Dir = "0" Index = "21197" Number = "1" Relife = "150000" County = "0" Enable = "true" Hide = "false" DeadScript = "NULL" LuaScript = "NULL" AIValue = "1000">
</MonsterGroupInfo>
</MonsterGroup>
<MonsterGroup>
<MonsterGroupInfo ZoneId = "11" X = "81.8561" Y = "38.0939" RandRange = "true" Dir = "0" Index = "21198" Number = "1" Relife = "150000" County = "0" Enable = "true" Hide = "false" DeadScript = "NULL" LuaScript = "NULL" AIValue = "1000">
</MonsterGroupInfo>
</MonsterGroup>
<MonsterGroup>
<MonsterGroupInfo ZoneId = "11" X = "81.932" Y = "40.2318" RandRange = "true" Dir = "0" Index = "21198" Number = "1" Relife = "150000" County = "0" Enable = "true" Hide = "false" DeadScript = "NULL" LuaScript = "NULL" AIValue = "1000">
</MonsterGroupInfo>
</MonsterGroup>
<MonsterGroup>
<MonsterGroupInfo ZoneId = "11" X = "82.1135" Y = "41.4181" RandRange = "true" Dir = "0" Index = "21198" Number = "1" Relife = "150000" County = "0" Enable = "true" Hide = "false" DeadScript = "NULL" LuaScript = "NULL" AIValue = "1000">
</MonsterGroupInfo>
</MonsterGroup>
<MonsterGroup>
<MonsterGroupInfo ZoneId = "11" X = "83.2594" Y = "42" RandRange = "true" Dir = "0" Index = "21198" Number = "1" Relife = "150000" County = "0" Enable = "true" Hide = "false" DeadScript = "NULL" LuaScript = "NULL" AIValue = "1000">
</MonsterGroupInfo>
</MonsterGroup>
<MonsterGroup>
<MonsterGroupInfo ZoneId = "11" X = "84.6274" Y = "41.5293" RandRange = "true" Dir = "0" Index = "21198" Number = "1" Relife = "150000" County = "0" Enable = "true" Hide = "false" DeadScript = "NULL" LuaScript = "NULL" AIValue = "1000">
</MonsterGroupInfo>
</MonsterGroup>
<MonsterGroup>
<MonsterGroupInfo ZoneId = "11" X = "86.2556" Y = "37.9239" RandRange = "true" Dir = "0" Index = "21198" Number = "1" Relife = "150000" County = "0" Enable = "true" Hide = "false" DeadScript = "NULL" LuaScript = "NULL" AIValue = "1000">
</MonsterGroupInfo>
</MonsterGroup>
<MonsterGroup>
<MonsterGroupInfo ZoneId = "11" X = "86.8925" Y = "37.9188" RandRange = "true" Dir = "0" Index = "21198" Number = "1" Relife = "150000" County = "0" Enable = "true" Hide = "false" DeadScript = "NULL" LuaScript = "NULL" AIValue = "1000">
</MonsterGroupInfo>
</MonsterGroup>
<MonsterGroup>
<MonsterGroupInfo ZoneId = "11" X = "87" Y = "41.9677" RandRange = "true" Dir = "0" Index = "21198" Number = "1" Relife = "150000" County = "0" Enable = "true" Hide = "false" DeadScript = "NULL" LuaScript = "NULL" AIValue = "1000">
</MonsterGroupInfo>
</MonsterGroup>
<MonsterGroup>
<MonsterGroupInfo ZoneId = "12" X = "81.848" Y = "41.7608" RandRange = "true" Dir = "0" Index = "21198" Number = "1" Relife = "150000" County = "0" Enable = "true" Hide = "false" DeadScript = "NULL" LuaScript = "NULL" AIValue = "1000">
</MonsterGroupInfo>
</MonsterGroup>
<MonsterGroup>
<MonsterGroupInfo ZoneId = "12" X = "82.3438" Y = "45.7047" RandRange = "true" Dir = "0" Index = "21198" Number = "1" Relife = "150000" County = "0" Enable = "true" Hide = "false" DeadScript = "NULL" LuaScript = "NULL" AIValue = "1000">
</MonsterGroupInfo>
</MonsterGroup>
<MonsterGroup>
<MonsterGroupInfo ZoneId = "12" X = "82.0307" Y = "47.9223" RandRange = "true" Dir = "0" Index = "21198" Number = "1" Relife = "150000" County = "0" Enable = "true" Hide = "false" DeadScript = "NULL" LuaScript = "NULL" AIValue = "1000">
</MonsterGroupInfo>
</MonsterGroup>
<MonsterGroup>
<MonsterGroupInfo ZoneId = "12" X = "85.0993" Y = "48" RandRange = "true" Dir = "0" Index = "21198" Number = "1" Relife = "150000" County = "0" Enable = "true" Hide = "false" DeadScript = "NULL" LuaScript = "NULL" AIValue = "1000">
</MonsterGroupInfo>
</MonsterGroup>
<MonsterGroup>
<MonsterGroupInfo ZoneId = "12" X = "84.8202" Y = "43.2398" RandRange = "true" Dir = "0" Index = "21198" Number = "1" Relife = "150000" County = "0" Enable = "true" Hide = "false" DeadScript = "NULL" LuaScript = "NULL" AIValue = "1000">
</MonsterGroupInfo>
</MonsterGroup>
<MonsterGroup>
<MonsterGroupInfo ZoneId = "12" X = "87" Y = "42.2592" RandRange = "true" Dir = "0" Index = "21198" Number = "1" Relife = "150000" County = "0" Enable = "true" Hide = "false" DeadScript = "NULL" LuaScript = "NULL" AIValue = "1000">
</MonsterGroupInfo>
</MonsterGroup>
<MonsterGroup>
<MonsterGroupInfo ZoneId = "12" X = "86.9964" Y = "47.9403" RandRange = "true" Dir = "0" Index = "21198" Number = "1" Relife = "150000" County = "0" Enable = "true" Hide = "false" DeadScript = "NULL" LuaScript = "NULL" AIValue = "1000">
</MonsterGroupInfo>
</MonsterGroup>
<MonsterGroup>
<MonsterGroupInfo ZoneId = "13" X = "79.4455" Y = "49.7197" RandRange = "true" Dir = "0" Index = "21198" Number = "1" Relife = "150000" County = "0" Enable = "true" Hide = "false" DeadScript = "NULL" LuaScript = "NULL" AIValue = "1000">
</MonsterGroupInfo>
</MonsterGroup>
<MonsterGroup>
<MonsterGroupInfo ZoneId = "13" X = "79.0368" Y = "52.9067" RandRange = "true" Dir = "0" Index = "21198" Number = "1" Relife = "150000" County = "0" Enable = "true" Hide = "false" DeadScript = "NULL" LuaScript = "NULL" AIValue = "1000">
</MonsterGroupInfo>
</MonsterGroup>
<MonsterGroup>
<MonsterGroupInfo ZoneId = "13" X = "80.8895" Y = "53.9082" RandRange = "true" Dir = "0" Index = "21198" Number = "1" Relife = "150000" County = "0" Enable = "true" Hide = "false" DeadScript = "NULL" LuaScript = "NULL" AIValue = "1000">
</MonsterGroupInfo>
</MonsterGroup>
<MonsterGroup>
<MonsterGroupInfo ZoneId = "13" X = "81.9469" Y = "53.3855" RandRange = "true" Dir = "0" Index = "21198" Number = "1" Relife = "150000" County = "0" Enable = "true" Hide = "false" DeadScript = "NULL" LuaScript = "NULL" AIValue = "1000">
</MonsterGroupInfo>
</MonsterGroup>
<MonsterGroup>
<MonsterGroupInfo ZoneId = "13" X = "84.8596" Y = "52.2929" RandRange = "true" Dir = "0" Index = "21198" Number = "1" Relife = "150000" County = "0" Enable = "true" Hide = "false" DeadScript = "NULL" LuaScript = "NULL" AIValue = "1000">
</MonsterGroupInfo>
</MonsterGroup>
<MonsterGroup>
<MonsterGroupInfo ZoneId = "13" X = "84.8466" Y = "53.7376" RandRange = "true" Dir = "0" Index = "21198" Number = "1" Relife = "150000" County = "0" Enable = "true" Hide = "false" DeadScript = "NULL" LuaScript = "NULL" AIValue = "1000">
</MonsterGroupInfo>
</MonsterGroup>
<MonsterGroup>
<MonsterGroupInfo ZoneId = "9" X = "82.7046" Y = "47.4651" RandRange = "true" Dir = "0" Index = "21198" Number = "1" Relife = "150000" County = "0" Enable = "true" Hide = "false" DeadScript = "NULL" LuaScript = "NULL" AIValue = "1000">
</MonsterGroupInfo>
</MonsterGroup>
<MonsterGroup>
<MonsterGroupInfo ZoneId = "9" X = "82.4759" Y = "49.6566" RandRange = "true" Dir = "0" Index = "21198" Number = "1" Relife = "150000" County = "0" Enable = "true" Hide = "false" DeadScript = "NULL" LuaScript = "NULL" AIValue = "1000">
</MonsterGroupInfo>
</MonsterGroup>
<MonsterGroup>
<MonsterGroupInfo ZoneId = "9" X = "82.7786" Y = "51" RandRange = "true" Dir = "0" Index = "21198" Number = "1" Relife = "150000" County = "0" Enable = "true" Hide = "false" DeadScript = "NULL" LuaScript = "NULL" AIValue = "1000">
</MonsterGroupInfo>
</MonsterGroup>
<MonsterGroup>
<MonsterGroupInfo ZoneId = "9" X = "85.0683" Y = "50.9698" RandRange = "true" Dir = "0" Index = "21198" Number = "1" Relife = "150000" County = "0" Enable = "true" Hide = "false" DeadScript = "NULL" LuaScript = "NULL" AIValue = "1000">
</MonsterGroupInfo>
</MonsterGroup>
<MonsterGroup>
<MonsterGroupInfo ZoneId = "9" X = "86.4835" Y = "49.7522" RandRange = "true" Dir = "0" Index = "21198" Number = "1" Relife = "150000" County = "0" Enable = "true" Hide = "false" DeadScript = "NULL" LuaScript = "NULL" AIValue = "1000">
</MonsterGroupInfo>
</MonsterGroup>
<MonsterGroup>
<MonsterGroupInfo ZoneId = "10" X = "81.4851" Y = "52.0509" RandRange = "true" Dir = "0" Index = "21198" Number = "1" Relife = "150000" County = "0" Enable = "true" Hide = "false" DeadScript = "NULL" LuaScript = "NULL" AIValue = "1000">
</MonsterGroupInfo>
</MonsterGroup>
<MonsterGroup>
<MonsterGroupInfo ZoneId = "10" X = "81.0618" Y = "53.5991" RandRange = "true" Dir = "0" Index = "21198" Number = "1" Relife = "150000" County = "0" Enable = "true" Hide = "false" DeadScript = "NULL" LuaScript = "NULL" AIValue = "1000">
</MonsterGroupInfo>
</MonsterGroup>
<MonsterGroup>
<MonsterGroupInfo ZoneId = "10" X = "85.1513" Y = "53.505" RandRange = "true" Dir = "0" Index = "21198" Number = "1" Relife = "150000" County = "0" Enable = "true" Hide = "false" DeadScript = "NULL" LuaScript = "NULL" AIValue = "1000">
</MonsterGroupInfo>
</MonsterGroup>
<MonsterGroup>
<MonsterGroupInfo ZoneId = "10" X = "87" Y = "52.1307" RandRange = "true" Dir = "0" Index = "21198" Number = "1" Relife = "150000" County = "0" Enable = "true" Hide = "false" DeadScript = "NULL" LuaScript = "NULL" AIValue = "1000">
</MonsterGroupInfo>
</MonsterGroup>
<MonsterGroup>
<MonsterGroupInfo ZoneId = "14" X = "74.3115" Y = "62.2751" RandRange = "true" Dir = "0" Index = "21198" Number = "1" Relife = "150000" County = "0" Enable = "true" Hide = "false" DeadScript = "NULL" LuaScript = "NULL" AIValue = "1000">
</MonsterGroupInfo>
</MonsterGroup>
<MonsterGroup>
<MonsterGroupInfo ZoneId = "14" X = "73.634" Y = "64.829" RandRange = "true" Dir = "0" Index = "21198" Number = "1" Relife = "150000" County = "0" Enable = "true" Hide = "false" DeadScript = "NULL" LuaScript = "NULL" AIValue = "1000">
</MonsterGroupInfo>
</MonsterGroup>
<MonsterGroup>
<MonsterGroupInfo ZoneId = "14" X = "76.7482" Y = "65" RandRange = "true" Dir = "0" Index = "21198" Number = "1" Relife = "150000" County = "0" Enable = "true" Hide = "false" DeadScript = "NULL" LuaScript = "NULL" AIValue = "1000">
</MonsterGroupInfo>
</MonsterGroup>
<MonsterGroup>
<MonsterGroupInfo ZoneId = "14" X = "77.0247" Y = "65" RandRange = "true" Dir = "0" Index = "21198" Number = "1" Relife = "150000" County = "0" Enable = "true" Hide = "false" DeadScript = "NULL" LuaScript = "NULL" AIValue = "1000">
</MonsterGroupInfo>
</MonsterGroup>
<MonsterGroup>
<MonsterGroupInfo ZoneId = "14" X = "79" Y = "62.5835" RandRange = "true" Dir = "0" Index = "21198" Number = "1" Relife = "150000" County = "0" Enable = "true" Hide = "false" DeadScript = "NULL" LuaScript = "NULL" AIValue = "1000">
</MonsterGroupInfo>
</MonsterGroup>
<MonsterGroup>
<MonsterGroupInfo ZoneId = "14" X = "79" Y = "61.9502" RandRange = "true" Dir = "0" Index = "21198" Number = "1" Relife = "150000" County = "0" Enable = "true" Hide = "false" DeadScript = "NULL" LuaScript = "NULL" AIValue = "1000">
</MonsterGroupInfo>
</MonsterGroup>
<MonsterGroup>
<MonsterGroupInfo ZoneId = "14" X = "79" Y = "65" RandRange = "true" Dir = "0" Index = "21198" Number = "1" Relife = "150000" County = "0" Enable = "true" Hide = "false" DeadScript = "NULL" LuaScript = "NULL" AIValue = "1000">
</MonsterGroupInfo>
</MonsterGroup>
<MonsterGroup>
<MonsterGroupInfo ZoneId = "15" X = "83.7159" Y = "69.4557" RandRange = "true" Dir = "0" Index = "21199" Number = "1" Relife = "150000" County = "0" Enable = "true" Hide = "false" DeadScript = "NULL" LuaScript = "NULL" AIValue = "1000">
</MonsterGroupInfo>
</MonsterGroup>
<MonsterGroup>
<MonsterGroupInfo ZoneId = "15" X = "83.5815" Y = "73.3069" RandRange = "true" Dir = "0" Index = "21199" Number = "1" Relife = "150000" County = "0" Enable = "true" Hide = "false" DeadScript = "NULL" LuaScript = "NULL" AIValue = "1000">
</MonsterGroupInfo>
</MonsterGroup>
<MonsterGroup>
<MonsterGroupInfo ZoneId = "15" X = "83.7001" Y = "74.7496" RandRange = "true" Dir = "0" Index = "21199" Number = "1" Relife = "150000" County = "0" Enable = "true" Hide = "false" DeadScript = "NULL" LuaScript = "NULL" AIValue = "1000">
</MonsterGroupInfo>
</MonsterGroup>
<MonsterGroup>
<MonsterGroupInfo ZoneId = "15" X = "84.7332" Y = "68.6992" RandRange = "true" Dir = "0" Index = "21199" Number = "1" Relife = "150000" County = "0" Enable = "true" Hide = "false" DeadScript = "NULL" LuaScript = "NULL" AIValue = "1000">
</MonsterGroupInfo>
</MonsterGroup>
<MonsterGroup>
<MonsterGroupInfo ZoneId = "15" X = "84.7262" Y = "70.3277" RandRange = "true" Dir = "0" Index = "21199" Number = "1" Relife = "150000" County = "0" Enable = "true" Hide = "false" DeadScript = "NULL" LuaScript = "NULL" AIValue = "1000">
</MonsterGroupInfo>
</MonsterGroup>
<MonsterGroup>
<MonsterGroupInfo ZoneId = "15" X = "86.65" Y = "72.454" RandRange = "true" Dir = "0" Index = "21199" Number = "1" Relife = "150000" County = "0" Enable = "true" Hide = "false" DeadScript = "NULL" LuaScript = "NULL" AIValue = "1000">
</MonsterGroupInfo>
</MonsterGroup>
<MonsterGroup>
<MonsterGroupInfo ZoneId = "16" X = "60.3192" Y = "85.8908" RandRange = "true" Dir = "0" Index = "21199" Number = "1" Relife = "150000" County = "0" Enable = "true" Hide = "false" DeadScript = "NULL" LuaScript = "NULL" AIValue = "1000">
</MonsterGroupInfo>
</MonsterGroup>
<MonsterGroup>
<MonsterGroupInfo ZoneId = "16" X = "60.0717" Y = "87.6604" RandRange = "true" Dir = "0" Index = "21199" Number = "1" Relife = "150000" County = "0" Enable = "true" Hide = "false" DeadScript = "NULL" LuaScript = "NULL" AIValue = "1000">
</MonsterGroupInfo>
</MonsterGroup>
<MonsterGroup>
<MonsterGroupInfo ZoneId = "16" X = "61.6184" Y = "87.8827" RandRange = "true" Dir = "0" Index = "21199" Number = "1" Relife = "150000" County = "0" Enable = "true" Hide = "false" DeadScript = "NULL" LuaScript = "NULL" AIValue = "1000">
</MonsterGroupInfo>
</MonsterGroup>
<MonsterGroup>
<MonsterGroupInfo ZoneId = "16" X = "63.6002" Y = "86.4222" RandRange = "true" Dir = "0" Index = "21199" Number = "1" Relife = "150000" County = "0" Enable = "true" Hide = "false" DeadScript = "NULL" LuaScript = "NULL" AIValue = "1000">
</MonsterGroupInfo>
</MonsterGroup>
<MonsterGroup>
<MonsterGroupInfo ZoneId = "16" X = "65.266" Y = "85.9753" RandRange = "true" Dir = "0" Index = "21199" Number = "1" Relife = "150000" County = "0" Enable = "true" Hide = "false" DeadScript = "NULL" LuaScript = "NULL" AIValue = "1000">
</MonsterGroupInfo>
</MonsterGroup>
<MonsterGroup>
<MonsterGroupInfo ZoneId = "16" X = "65.5952" Y = "86.7151" RandRange = "true" Dir = "0" Index = "21199" Number = "1" Relife = "150000" County = "0" Enable = "true" Hide = "false" DeadScript = "NULL" LuaScript = "NULL" AIValue = "1000">
</MonsterGroupInfo>
</MonsterGroup>
<MonsterGroup>
<MonsterGroupInfo ZoneId = "16" X = "66" Y = "88" RandRange = "true" Dir = "0" Index = "21199" Number = "1" Relife = "150000" County = "0" Enable = "true" Hide = "false" DeadScript = "NULL" LuaScript = "NULL" AIValue = "1000">
</MonsterGroupInfo>
</MonsterGroup>
<MonsterGroup>
<MonsterGroupInfo ZoneId = "17" X = "82.427" Y = "68.1135" RandRange = "true" Dir = "0" Index = "21199" Number = "1" Relife = "150000" County = "0" Enable = "true" Hide = "false" DeadScript = "NULL" LuaScript = "NULL" AIValue = "1000">
</MonsterGroupInfo>
</MonsterGroup>
<MonsterGroup>
<MonsterGroupInfo ZoneId = "17" X = "81.8698" Y = "70.4282" RandRange = "true" Dir = "0" Index = "21199" Number = "1" Relife = "150000" County = "0" Enable = "true" Hide = "false" DeadScript = "NULL" LuaScript = "NULL" AIValue = "1000">
</MonsterGroupInfo>
</MonsterGroup>
<MonsterGroup>
<MonsterGroupInfo ZoneId = "17" X = "85.3768" Y = "68.2146" RandRange = "true" Dir = "0" Index = "21199" Number = "1" Relife = "150000" County = "0" Enable = "true" Hide = "false" DeadScript = "NULL" LuaScript = "NULL" AIValue = "1000">
</MonsterGroupInfo>
</MonsterGroup>
<MonsterGroup>
<MonsterGroupInfo ZoneId = "17" X = "85.7446" Y = "69.0517" RandRange = "true" Dir = "0" Index = "21199" Number = "1" Relife = "150000" County = "0" Enable = "true" Hide = "false" DeadScript = "NULL" LuaScript = "NULL" AIValue = "1000">
</MonsterGroupInfo>
</MonsterGroup>
<MonsterGroup>
<MonsterGroupInfo ZoneId = "17" X = "86" Y = "71.4727" RandRange = "true" Dir = "0" Index = "21199" Number = "1" Relife = "150000" County = "0" Enable = "true" Hide = "false" DeadScript = "NULL" LuaScript = "NULL" AIValue = "1000">
</MonsterGroupInfo>
</MonsterGroup>
<MonsterGroup>
<MonsterGroupInfo ZoneId = "17" X = "86" Y = "72" RandRange = "true" Dir = "0" Index = "21199" Number = "1" Relife = "150000" County = "0" Enable = "true" Hide = "false" DeadScript = "NULL" LuaScript = "NULL" AIValue = "1000">
</MonsterGroupInfo>
</MonsterGroup>
<MonsterGroup>
<MonsterGroupInfo ZoneId = "18" X = "78.522" Y = "82.9589" RandRange = "true" Dir = "0" Index = "21199" Number = "1" Relife = "150000" County = "0" Enable = "true" Hide = "false" DeadScript = "NULL" LuaScript = "NULL" AIValue = "1000">
</MonsterGroupInfo>
</MonsterGroup>
<MonsterGroup>
<MonsterGroupInfo ZoneId = "18" X = "78.9339" Y = "84.8628" RandRange = "true" Dir = "0" Index = "21199" Number = "1" Relife = "150000" County = "0" Enable = "true" Hide = "false" DeadScript = "NULL" LuaScript = "NULL" AIValue = "1000">
</MonsterGroupInfo>
</MonsterGroup>
<MonsterGroup>
<MonsterGroupInfo ZoneId = "18" X = "79.1908" Y = "85.8944" RandRange = "true" Dir = "0" Index = "21199" Number = "1" Relife = "150000" County = "0" Enable = "true" Hide = "false" DeadScript = "NULL" LuaScript = "NULL" AIValue = "1000">
</MonsterGroupInfo>
</MonsterGroup>
<MonsterGroup>
<MonsterGroupInfo ZoneId = "18" X = "85" Y = "85.5617" RandRange = "true" Dir = "0" Index = "21199" Number = "1" Relife = "150000" County = "0" Enable = "true" Hide = "false" DeadScript = "NULL" LuaScript = "NULL" AIValue = "1000">
</MonsterGroupInfo>
</MonsterGroup>
<MonsterGroup>
<MonsterGroupInfo ZoneId = "18" X = "84.0459" Y = "86" RandRange = "true" Dir = "0" Index = "21199" Number = "1" Relife = "150000" County = "0" Enable = "true" Hide = "false" DeadScript = "NULL" LuaScript = "NULL" AIValue = "1000">
</MonsterGroupInfo>
</MonsterGroup>
<MonsterGroup>
<MonsterGroupInfo ZoneId = "18" X = "81.0182" Y = "85.2119" RandRange = "true" Dir = "0" Index = "21199" Number = "1" Relife = "150000" County = "0" Enable = "true" Hide = "false" DeadScript = "NULL" LuaScript = "NULL" AIValue = "1000">
</MonsterGroupInfo>
</MonsterGroup>
<MonsterGroup>
<MonsterGroupInfo ZoneId = "19" X = "76.9672" Y = "83.9556" RandRange = "true" Dir = "0" Index = "21199" Number = "1" Relife = "150000" County = "0" Enable = "true" Hide = "false" DeadScript = "NULL" LuaScript = "NULL" AIValue = "1000">
</MonsterGroupInfo>
</MonsterGroup>
<MonsterGroup>
<MonsterGroupInfo ZoneId = "19" X = "76.0352" Y = "85.5397" RandRange = "true" Dir = "0" Index = "21199" Number = "1" Relife = "150000" County = "0" Enable = "true" Hide = "false" DeadScript = "NULL" LuaScript = "NULL" AIValue = "1000">
</MonsterGroupInfo>
</MonsterGroup>
<MonsterGroup>
<MonsterGroupInfo ZoneId = "19" X = "77.2364" Y = "86" RandRange = "true" Dir = "0" Index = "21199" Number = "1" Relife = "150000" County = "0" Enable = "true" Hide = "false" DeadScript = "NULL" LuaScript = "NULL" AIValue = "1000">
</MonsterGroupInfo>
</MonsterGroup>
<MonsterGroup>
<MonsterGroupInfo ZoneId = "19" X = "78.6699" Y = "84.5507" RandRange = "true" Dir = "0" Index = "21199" Number = "1" Relife = "150000" County = "0" Enable = "true" Hide = "false" DeadScript = "NULL" LuaScript = "NULL" AIValue = "1000">
</MonsterGroupInfo>
</MonsterGroup>
<MonsterGroup>
<MonsterGroupInfo ZoneId = "19" X = "81" Y = "84.8321" RandRange = "true" Dir = "0" Index = "21199" Number = "1" Relife = "150000" County = "0" Enable = "true" Hide = "false" DeadScript = "NULL" LuaScript = "NULL" AIValue = "1000">
</MonsterGroupInfo>
</MonsterGroup>
<MonsterGroup>
<MonsterGroupInfo ZoneId = "19" X = "80.4497" Y = "86" RandRange = "true" Dir = "0" Index = "21199" Number = "1" Relife = "150000" County = "0" Enable = "true" Hide = "false" DeadScript = "NULL" LuaScript = "NULL" AIValue = "1000">
</MonsterGroupInfo>
</MonsterGroup>
<MonsterGroup>
<MonsterGroupInfo ZoneId = "19" X = "75" Y = "84.1579" RandRange = "true" Dir = "0" Index = "21199" Number = "1" Relife = "150000" County = "0" Enable = "true" Hide = "false" DeadScript = "NULL" LuaScript = "NULL" AIValue = "1000">
</MonsterGroupInfo>
</MonsterGroup>
</Monster>
</Stage>
